setup.py
quetzalcoatl/__init__.py
quetzalcoatl/image_processing.py
quetzalcoatl.egg-info/PKG-INFO
quetzalcoatl.egg-info/SOURCES.txt
quetzalcoatl.egg-info/dependency_links.txt
quetzalcoatl.egg-info/not-zip-safe
quetzalcoatl.egg-info/requires.txt
quetzalcoatl.egg-info/top_level.txt