Metadata-Version: 1.0
Name: quetzalcoatl
Version: 0.1.3
Summary: An image processing and computer vision toolbox/library
Home-page: http://github.com/colmex/quetzalcoatl
Author: Luis Hernandez
Author-email: luisfmh@gmail.com
License: MIT
Platform: UNKNOWN
